alchemy_mock/__init__.py
alchemy_mock/comparison.py
alchemy_mock/compat.py
alchemy_mock/mocking.py
alchemy_mock/unittests.py
alchemy_mock/utils.py
alchemy_mock-0.4.2.dist-info/AUTHORS.rst
alchemy_mock-0.4.2.dist-info/LICENSE.rst
alchemy_mock-0.4.2.dist-info/METADATA
alchemy_mock-0.4.2.dist-info/WHEEL
alchemy_mock-0.4.2.dist-info/top_level.txt
alchemy_mock-0.4.2.dist-info/RECORD
