Metadata-Version: 2.1
Name: alchemy-mock
Version: 0.4.2
Summary: SQLAlchemy mock helpers.
Home-page: https://github.com/miki725/alchemy-mock
Author: Miroslav Shubernetskiy
Author-email: UNKNOWN
License: MIT
Keywords: sqlalchemy mock testing
Platform: UNKNOWN
Classifier: Intended Audience :: Developers
Classifier: Natural Language :: English
Classifier: License :: OSI Approved :: MIT License
Classifier: Programming Language :: Python
Classifier: Programming Language :: Python :: 2.7
Classifier: Programming Language :: Python :: 3
Classifier: Programming Language :: Python :: 3.6
Classifier: Development Status :: 2 - Pre-Alpha
Requires-Dist: six
Requires-Dist: sqlalchemy
Requires-Dist: setuptools
